qiskit_sphinx_theme/__init__.py
qiskit_sphinx_theme/assets/scripts/qiskit-sphinx-theme.js
qiskit_sphinx_theme/assets/styles/_admonitions.scss
qiskit_sphinx_theme/assets/styles/_api.scss
qiskit_sphinx_theme/assets/styles/_colors.scss
qiskit_sphinx_theme/assets/styles/_custom-directives.scss
qiskit_sphinx_theme/assets/styles/_drop-shadows.scss
qiskit_sphinx_theme/assets/styles/_icons.scss
qiskit_sphinx_theme/assets/styles/_layout.scss
qiskit_sphinx_theme/assets/styles/_left-sidebar.scss
qiskit_sphinx_theme/assets/styles/_mobile-header.scss
qiskit_sphinx_theme/assets/styles/_scaffold.scss
qiskit_sphinx_theme/assets/styles/_sphinx-extensions.scss
qiskit_sphinx_theme/assets/styles/_tables.scss
qiskit_sphinx_theme/assets/styles/_theme.scss
qiskit_sphinx_theme/assets/styles/_typography.scss
qiskit_sphinx_theme/assets/styles/qiskit-sphinx-theme.scss
qiskit_sphinx_theme/directives.py
qiskit_sphinx_theme/previous_releases.py
qiskit_sphinx_theme/theme/qiskit-sphinx-theme/base.html
qiskit_sphinx_theme/theme/qiskit-sphinx-theme/custom_templates/extra_head.html
qiskit_sphinx_theme/theme/qiskit-sphinx-theme/custom_templates/sidebar_brand.html
qiskit_sphinx_theme/theme/qiskit-sphinx-theme/custom_templates/sidebar_languages.html
qiskit_sphinx_theme/theme/qiskit-sphinx-theme/custom_templates/sidebar_version_list.html
qiskit_sphinx_theme/theme/qiskit-sphinx-theme/partials/icons.html
qiskit_sphinx_theme/theme/qiskit-sphinx-theme/static/images/logo.png
qiskit_sphinx_theme/theme/qiskit-sphinx-theme/static/scripts/qiskit-sphinx-theme.js
qiskit_sphinx_theme/theme/qiskit-sphinx-theme/static/styles/qiskit-sphinx-theme.css
qiskit_sphinx_theme/theme/qiskit-sphinx-theme/static/styles/qiskit-sphinx-theme.css.map
qiskit_sphinx_theme/theme/qiskit-sphinx-theme/theme.conf
qiskit_sphinx_theme/translations.py
qiskit_sphinx_theme-2.0.0.dist-info/LICENSE
qiskit_sphinx_theme-2.0.0.dist-info/METADATA
qiskit_sphinx_theme-2.0.0.dist-info/WHEEL
qiskit_sphinx_theme-2.0.0.dist-info/entry_points.txt
qiskit_sphinx_theme-2.0.0.dist-info/RECORD