Metadata-Version: 2.1
Name: qiskit-sphinx-theme
Version: 2.0.0
Summary: A Sphinx theme for Qiskit and Qiskit Ecosystem projects
Author-Email: Qiskit Development Team <qiskit@us.ibm.com>
License:                    Copyright 2020 IBM and its contributors
Classifier: Development Status :: 5 - Production/Stable
Classifier: Environment :: Web Environment
Classifier: Intended Audience :: Developers
Classifier: Intended Audience :: System Administrators
Classifier: License :: OSI Approved :: Apache Software License
Classifier: Operating System :: OS Independent
Classifier: Programming Language :: Python
Classifier: Topic :: Internet
Classifier: Topic :: Software Development :: Documentation
Classifier: Framework :: Sphinx :: Theme
Project-URL: Bug tracker, https://github.com/Qiskit/qiskit_sphinx_theme/issues
Project-URL: Source code, https://github.com/Qiskit/qiskit_sphinx_theme
Requires-Dist: docutils
Requires-Dist: sphinx<9.0,>=6.0
Requires-Dist: furo==2024.8.6
